Metadata-Version: 1.0
Name: wxz-decrpty
Version: 0.0.3
Summary: 微小助
Home-page: https://gitlab.yunkecn.com/frontend/weixiaozhu-electron
Author: wujiantao
Author-email: wujiantao@yunke.ai
License: UNKNOWN
Platform: UNKNOWN
